superlive/__init__.py
superlive/core/__init__.py
superlive/core/http_client.py
superlive/streams/__init__.py
superlive/streams/host.py
superlive-1.2.2.dist-info/LICENSE
superlive-1.2.2.dist-info/METADATA
superlive-1.2.2.dist-info/WHEEL
superlive-1.2.2.dist-info/top_level.txt
superlive-1.2.2.dist-info/RECORD
