Metadata-Version: 2.1
Name: superlive
Version: 1.2.2
Summary: Superlive Python SDK
Home-page: https://github.com/sophatahsher/superlive_sdk_python
Author: DR-Tech
Author-email: dev@dr-tech.co
Project-URL: Bug Tracker, https://github.com/sophatahsher/superlive_sdk_python/-/issues
Project-URL: repository, https://github.com/sophatahsher/superlive_sdk_python
Keywords: Superlive
Classifier: Programming Language :: Python :: 3.9
Requires-Python: >=3.6
License-File: LICENSE
Requires-Dist: certifi (==2022.12.7)
Requires-Dist: charset-normalizer (==3.1.0)
Requires-Dist: idna (==3.4)
Requires-Dist: requests (==2.29.0)
Requires-Dist: urllib3 (==1.26.15)
